pyDecLog.py
pyDecLog-0.1.7.dist-info/LICENSE
pyDecLog-0.1.7.dist-info/METADATA
pyDecLog-0.1.7.dist-info/WHEEL
pyDecLog-0.1.7.dist-info/top_level.txt
pyDecLog-0.1.7.dist-info/RECORD
