Metadata-Version: 2.1
Name: pyDecLog
Version: 0.1.7
Summary: pyDecLog: a Python module for logging via decorators
Home-page: https://github.com/kyaiooiayk/pyDecLog
Author: kyaiooiayk
Author-email: kayaiooiayk@email.com
License: MIT
Classifier: Programming Language :: Python :: 3.9
Requires-Python: >=3.9
License-File: LICENSE
Requires-Dist: pympler (>=1.0.1)
Requires-Dist: numpy (>=1.21.6)
